gTixi/Dianzhen.ttf
gTixi/SSD1306.py
gTixi/__init__.py
gTixi/alib.py
gTixi/gpioPins.py
gTixi/starMod.py
gTixi/starServer.py
gTixi/wLTR390.py
gTixi/waDrivers.py
gTixi/waFile.py
gTixi/waText.py
gTixi/wadapter.py
gTixi/gpio4/__init__.py
gTixi/gpio4/arduino.py
gTixi/gpio4/constants.py
gTixi/stardevice/favicon.ico
gTixi/stardevice/index.html
gTixi/stardevice/socket.io.js
gTixi/stardevice/vue.global.js
gTixi/stardevice/vue.prod.js
gTixi-1.2.0.dist-info/LICENSE
gTixi-1.2.0.dist-info/METADATA
gTixi-1.2.0.dist-info/WHEEL
gTixi-1.2.0.dist-info/top_level.txt
gTixi-1.2.0.dist-info/RECORD
