Metadata-Version: 2.1
Name: gTixi
Version: 1.2.0
Summary: 高效碳基演示体系核心模块
Home-page: https://gitee.com/lxwk1spectre/walartminstar
Author: Spectre Lee
Author-email: lxwk1spectre@foxmail.com
Classifier: Programming Language :: Python :: 3
Classifier: License :: OSI Approved :: MIT License
Classifier: Operating System :: OS Independent
License-File: LICENSE
